[{"__type__":"cc.SpriteFrame","content":{"name":"img_rapid","texture":"09b23146-cafe-40b0-9bb1-1fa426aeea95","rect":[1613,1,236,236],"offset":[0,0],"originalSize":[242,242]}},[{"__type__":"cc.Prefab","_name":"SiderItem","data":{"__id__":1},"asyncLoadAssets":false},{"__type__":"cc.Node","_name":"SiderItem","_children":[{"__id__":2},{"__id__":9}],"_components":[{"__type__":"709520vV79GyqNnFkG+UooR","node":{"__id__":1},"item1":{"__id__":2},"itemIcon1":{"__id__":4},"itemName1":{"__id__":8},"item2":{"__id__":9},"itemIcon2":{"__id__":11},"itemName2":{"__id__":15}}],"_prefab":{"__type__":"cc.PrefabInfo","root":{"__id__":1},"fileId":"133abDtwH9ENKzB2SHFc2Ej"},"_contentSize":{"__type__":"cc.Size","width":440,"height":195},"_position":{"__type__":"cc.Vec2","x":556,"y":185}},{"__type__":"cc.Node","_name":"ItemNode1","_parent":{"__id__":1},"_children":[{"__id__":3},{"__id__":5},{"__id__":6}],"_components":[{"__type__":"cc.Button","node":{"__id__":2},"clickEvents":[{"__type__":"cc.ClickEvent","target":{"__id__":1},"component":"SiderItem","handler":"touchEnd1"}],"_N$target":{"__id__":2}}],"_prefab":{"__type__":"cc.PrefabInfo","root":{"__id__":1},"fileId":"39b59JWCktKxbcsWN/i4Cqo"},"_contentSize":{"__type__":"cc.Size","width":232,"height":232},"_position":{"__type__":"cc.Vec2","x":-116,"y":14.6}},{"__type__":"cc.Node","_name":"Icon1","_parent":{"__id__":2},"_components":[{"__id__":4}],"_prefab":{"__type__":"cc.PrefabInfo","root":{"__id__":1},"fileId":"2692dw7AwdF7L4uIkM/P/rr"},"_contentSize":{"__type__":"cc.Size","width":232,"height":232},"_scaleX":0.65,"_scaleY":0.65,"_position":{"__type__":"cc.Vec2","x":7,"y":7.4}},{"__type__":"cc.Sprite","node":{"__id__":3}},{"__type__":"cc.Node","_name":"Mask1","_parent":{"__id__":2},"_components":[{"__type__":"cc.Sprite","node":{"__id__":5},"_spriteFrame":{"__uuid__":"35a8b196-6f97-4418-832b-cc3c1ebd90dc"}}],"_prefab":{"__type__":"cc.PrefabInfo","root":{"__id__":1},"fileId":"02a78FQ+uVO2ZWmIDJtx9D9"},"_contentSize":{"__type__":"cc.Size","width":236,"height":236},"_scaleX":0.65,"_scaleY":0.65,"_position":{"__type__":"cc.Vec2","x":7,"y":7.4}},{"__type__":"cc.Node","_name":"NameBg1","_parent":{"__id__":2},"_children":[{"__id__":7}],"_components":[{"__type__":"cc.Sprite","node":{"__id__":6},"_spriteFrame":{"__uuid__":"cb119bdb-fa58-404f-9b85-5b608b73b951"}}],"_prefab":{"__type__":"cc.PrefabInfo","root":{"__id__":1},"fileId":"abe15t/9CtAYYJrjDfdPZhe"},"_contentSize":{"__type__":"cc.Size","width":213,"height":38},"_position":{"__type__":"cc.Vec2","x":7,"y":-91.6}},{"__type__":"cc.Node","_name":"SiderNick1","_parent":{"__id__":6},"_components":[{"__id__":8}],"_prefab":{"__type__":"cc.PrefabInfo","root":{"__id__":1},"fileId":"5f8a4dDt1RAJb/1IHyQJrhE"},"_contentSize":{"__type__":"cc.Size","width":96,"height":30}},{"__type__":"cc.Label","node":{"__id__":7},"_useOriginalSize":false,"_actualFontSize":24,"_fontSize":24,"_lineHeight":30,"_N$file":{"__uuid__":"9a28db59-06f3-4108-9b61-962e65ef8ab2"},"_isSystemFontUsed":false,"_N$string":"吃瓜群众","_N$horizontalAlign":1,"_N$verticalAlign":1},{"__type__":"cc.Node","_name":"ItemNode2","_parent":{"__id__":1},"_children":[{"__id__":10},{"__id__":12},{"__id__":13}],"_components":[{"__type__":"cc.Button","node":{"__id__":9},"clickEvents":[{"__type__":"cc.ClickEvent","target":{"__id__":1},"component":"SiderItem","handler":"touchEnd2"}],"_N$target":{"__id__":9}}],"_prefab":{"__type__":"cc.PrefabInfo","root":{"__id__":1},"fileId":"f506cMuHVhAhp459O06risr"},"_contentSize":{"__type__":"cc.Size","width":232,"height":232},"_position":{"__type__":"cc.Vec2","x":98.7,"y":16.6}},{"__type__":"cc.Node","_name":"Icon2","_parent":{"__id__":9},"_components":[{"__id__":11}],"_prefab":{"__type__":"cc.PrefabInfo","root":{"__id__":1},"fileId":"3b587k323BNN5/my8ujaMj4"},"_contentSize":{"__type__":"cc.Size","width":232,"height":232},"_scaleX":0.65,"_scaleY":0.65,"_position":{"__type__":"cc.Vec2","x":7.3,"y":5.4}},{"__type__":"cc.Sprite","node":{"__id__":10}},{"__type__":"cc.Node","_name":"Mask2","_parent":{"__id__":9},"_components":[{"__type__":"cc.Sprite","node":{"__id__":12},"_spriteFrame":{"__uuid__":"35a8b196-6f97-4418-832b-cc3c1ebd90dc"}}],"_prefab":{"__type__":"cc.PrefabInfo","root":{"__id__":1},"fileId":"ac1e1/7k/JIi6zK8YDfkpca"},"_contentSize":{"__type__":"cc.Size","width":236,"height":236},"_scaleX":0.65,"_scaleY":0.65,"_position":{"__type__":"cc.Vec2","x":7.3,"y":5.4}},{"__type__":"cc.Node","_name":"NameBg2","_parent":{"__id__":9},"_children":[{"__id__":14}],"_components":[{"__type__":"cc.Sprite","node":{"__id__":13},"_spriteFrame":{"__uuid__":"cb119bdb-fa58-404f-9b85-5b608b73b951"}}],"_prefab":{"__type__":"cc.PrefabInfo","root":{"__id__":1},"fileId":"367c3vEROFEGLlgYHE1NHhx"},"_contentSize":{"__type__":"cc.Size","width":213,"height":38},"_position":{"__type__":"cc.Vec2","x":9.3,"y":-93.6}},{"__type__":"cc.Node","_name":"SiderNick2","_parent":{"__id__":13},"_components":[{"__id__":15}],"_prefab":{"__type__":"cc.PrefabInfo","root":{"__id__":1},"fileId":"4161dTQFPVHmaShjG5NMWA3"},"_contentSize":{"__type__":"cc.Size","width":96,"height":30}},{"__type__":"cc.Label","node":{"__id__":14},"_useOriginalSize":false,"_actualFontSize":24,"_fontSize":24,"_lineHeight":30,"_N$file":{"__uuid__":"9a28db59-06f3-4108-9b61-962e65ef8ab2"},"_isSystemFontUsed":false,"_N$string":"吃瓜群众","_N$horizontalAlign":1,"_N$verticalAlign":1}],{"__type__":"cc.SpriteFrame","content":{"name":"img_floor14","texture":"09b23146-cafe-40b0-9bb1-1fa426aeea95","rect":[1798,239,213,38],"offset":[0,0],"originalSize":[217,42],"rotated":1}}]