{
  "Merge Bistro": "梦幻合成餐厅",
  "NotEnoughCoins": "钻石不足",
  "LivesShopWindow.products.buyEnergy": "%{restoreAmount}",
  "LivesShopWindow.products.energyForVideo": "X30",
  "LivesShopWindow.products.energyLottery": "高达%{restoreAmount}的能量",
  "LivesShopWindow.products.softCurrencySmall": "X%{amount}",
  "LivesShopWindow.products.softCurrencyMedium": "X%{amount}",
  "LivesShopWindow.products.softCurrencyLarge": "X%{amount}",
  "SpeedUpWindow.title": "立即完成",
  "SpeedUpWindow.text": "立即完成这个操作吗？",
  "SpeedUpWindow.stop": "停止",
  "SpeedUpWindow.hint": "观看视频并加快%{minutes}分钟!",
  "UseGoldButton.free": "免费",
  "OrdersWindow.orders.button.make": "订单",
  "OrdersWindow.orders.button.claim": "领取",
  "OrdersWindow.orders.reward": "奖励：",
  "OrdersWindow.orders.placeholder": "目前没有可用的订单。",
  "OrdersWindow.icons.required": "需要",
  "NewRecipesWindow.recipes.title": "有新的菜谱可用",
  "BuyIngredientsWindow.title": "购买食材",
  "BuyIngredientsWindow.text": "购买缺少的食材吗？",
  "chest": "宝箱",
  "sack": "解雇",
  "OpenChestWindow.title": "打开%{name}",
  "OpenChestWindow.question": "是否要打开这个%{name}？",
  "OpenChestWindow.suggestion": "可能含有：",
  "OpenChestWindow.button": "打开",
  "Buildable.info.title": "建筑：",
  "InfoView.button.go": "现在开始",
  "InfoView.button.build": "发送",
  "InfoView.button.instant": "立即",
  "Units.wood.name": "原木",
  "Units.wood.stage1.name": "木板",
  "Units.wood.stage2.name": "木板堆",
  "Units.wood.stage3.name": "木框架",
  "Units.wood.stage4.name": "小厨屋",
  "Units.wood.stage5.name": "飘香面包房",
  "Units.wood.stage6.name": "宽敞的食堂",
  "Units.wood.stage7.name": "华丽小酒馆",
  "Units.wood.stage8.name": "高级饭馆",
  "Units.wood.stage9.name": "建造",
  "Units.wood.stage10.name": "奢华大饭店",
  "Units.lava.name": "熔岩",
  "Units.lava.stage1.name": "熔岩石块",
  "Units.lava.stage2.name": "熔岩砾石",
  "Units.lava.stage3.name": "熔岩框架",
  "Units.lava.stage4.name": "火花锻炉",
  "Units.lava.stage5.name": "灼热熔炉",
  "Units.lava.stage6.name": "灼热铸造厂",
  "Units.lava.stage7.name": "烈焰车间",
  "Units.lava.stage8.name": "烈焰工坊",
  "Units.lava.stage9.name": "高级厨具厂",
  "Units.lava.stage10.name": "建造",
  "Units.lava.stage11.name": "至尊厨具厂",
  "Units.jade.name": "翡翠",
  "Units.jade.stage1.name": "翡翠细砾",
  "Units.jade.stage2.name": "翡翠细柱",
  "Units.jade.stage3.name": "翡翠框架",
  "Units.jade.stage4.name": "翡翠教室",
  "Units.jade.stage5.name": "王室训练营",
  "Units.jade.stage6.name": "烹饪学校",
  "Units.jade.stage7.name": "传承学院",
  "Units.jade.stage8.name": "大学院",
  "Units.jade.stage9.name": "庄严的大学",
  "Units.jade.stage10.name": "建造",
  "Units.jade.stage11.name": "皇家烹饪大学院",
  "Units.metal.name": "金属",
  "Units.metal.stage1.name": "矿石碎片",
  "Units.metal.stage2.name": "矿石块",
  "Units.metal.stage3.name": "金属框架",
  "Units.metal.stage4.name": "美食品鉴会",
  "Units.metal.stage5.name": "美食家组织",
  "Units.metal.stage6.name": "餐饮俱乐部",
  "Units.metal.stage7.name": "烹饪协会",
  "Units.metal.stage8.name": "烹饪大联盟",
  "Units.metal.stage9.name": "美食行业联合会",
  "Units.metal.stage10.name": "建造",
  "Units.metal.stage11.name": "传说食材公会",
  "Units.ice.name": "寒冰",
  "Units.ice.stage1.name": "冰块",
  "Units.ice.stage2.name": "冰板",
  "Units.ice.stage3.name": "冰框架",
  "Units.ice.stage4.name": "北极观察塔",
  "Units.ice.stage5.name": "冰霜炮塔",
  "Units.ice.stage6.name": "冰冻要塞",
  "Units.ice.stage7.name": "霜冻大本营",
  "Units.ice.stage8.name": "极冻城堡",
  "Units.ice.stage9.name": "极地棱垒",
  "Units.ice.stage10.name": "冰封堡垒",
  "Units.ice.stage11.name": "建造",
  "Units.ice.stage12.name": "冰封美食宫殿",
  "Units.cloth.name": "布料",
  "Units.cloth.stage1.name": "布匹",
  "Units.cloth.stage2.name": "布匹堆",
  "Units.cloth.stage3.name": "织布机",
  "Units.cloth.stage4.name": "扎染场",
  "Units.cloth.stage5.name": "布匹晾晒场",
  "Units.cloth.stage6.name": "布匹店",
  "Units.cloth.stage7.name": "豪华布匹店",
  "Units.cloth.stage8.name": "布料协会",
  "Units.cloth.stage9.name": "布料研究所",
  "Units.cloth.stage10.name": "布料基地",
  "Units.cloth.stage11.name": "建造",
  "Units.cloth.stage12.name": "全球布料协会",
  "Units.japan.name": "料理店",
  "Units.japan.stage1.name": "砖块",
  "Units.japan.stage2.name": "砖块堆",
  "Units.japan.stage3.name": "地基",
  "Units.japan.stage4.name": "院墙",
  "Units.japan.stage5.name": "关东煮",
  "Units.japan.stage6.name": "寿司店",
  "Units.japan.stage7.name": "烤鱼店",
  "Units.japan.stage8.name": "寿喜烧",
  "Units.japan.stage9.name": "拉面店",
  "Units.japan.stage10.name": "炸猪排店",
  "Units.japan.stage11.name": "建造",
  "Units.japan.stage12.name": "刺身料理店",
  "Units.wheat.name": "土豆",
  "Units.wheat.stage1.name": "土豆种",
  "Units.wheat.stage2.name": "土豆叶",
  "Units.wheat.stage3.name": "土豆茎",
  "Units.wheat.stage4.name": "旺盛的土豆",
  "Units.wheat.stage5.name": "土豆",
  "Units.wheat.stage6.name": "衰败的土豆",
  "Units.candies.name": "甘蔗",
  "Units.candies.stage1.name": "甘蔗苗",
  "Units.candies.stage2.name": "甘蔗杆",
  "Units.candies.stage3.name": "甘蔗枝",
  "Units.candies.stage4.name": "甘蔗田",
  "Units.candies.stage5.name": "甘蔗",
  "Units.candies.stage6.name": "衰败的甘蔗",
  "Units.apple.name": "大豆",
  "Units.apple.stage1.name": "大豆芽",
  "Units.apple.stage2.name": "大豆叶",
  "Units.apple.stage3.name": "大豆株",
  "Units.apple.stage4.name": "旺盛的大豆",
  "Units.apple.stage5.name": "大豆",
  "Units.apple.stage6.name": "衰败的大豆",
  "Units.strawberry.name": "葡萄",
  "Units.strawberry.stage1.name": "葡萄种子",
  "Units.strawberry.stage2.name": "葡萄叶",
  "Units.strawberry.stage3.name": "葡萄藤",
  "Units.strawberry.stage4.name": "茂盛的葡萄",
  "Units.strawberry.stage5.name": "葡萄",
  "Units.strawberry.stage6.name": "衰败的葡萄藤",
  "Units.mushrooms.name": "橘子",
  "Units.mushrooms.stage1.name": "橘子籽",
  "Units.mushrooms.stage2.name": "橘子苗",
  "Units.mushrooms.stage3.name": "橘子树",
  "Units.mushrooms.stage4.name": "橘子林",
  "Units.mushrooms.stage5.name": "橘子",
  "Units.mushrooms.stage6.name": "衰败的橘子树",
  "Units.corn.name": "蘑菇",
  "Units.corn.stage1.name": "蘑菇孢子",
  "Units.corn.stage2.name": "蘑菇苗",
  "Units.corn.stage3.name": "野蘑菇",
  "Units.corn.stage4.name": "成熟蘑菇",
  "Units.corn.stage5.name": "蘑菇",
  "Units.corn.stage6.name": "衰败的的蘑菇",
  "Units.treasure.name": "财宝",
  "Units.treasure.stage1.name": "普通宝箱",
  "Units.treasure.stage2.name": "稀有宝箱",
  "Units.treasure.stage3.name": "史诗宝箱",
  "Units.sacks.name": "食材盒",
  "Units.sacks.stage1.name": "普通宝箱",
  "Units.sacks.stage2.name": "稀有宝箱",
  "Units.sacks.stage3.name": "史诗宝箱",
  "Units.woodchest.name": "原木",
  "Units.woodchest.stage1.name": "普通宝箱",
  "Units.woodchest.stage2.name": "稀有宝箱",
  "Units.woodchest.stage3.name": "史诗宝箱",
  "Units.lavachest.name": "熔岩",
  "Units.lavachest.stage1.name": "普通宝箱",
  "Units.lavachest.stage2.name": "稀有宝箱",
  "Units.lavachest.stage3.name": "史诗宝箱",
  "Units.jadechest.name": "翡翠",
  "Units.jadechest.stage1.name": "普通宝箱",
  "Units.jadechest.stage2.name": "稀有宝箱",
  "Units.jadechest.stage3.name": "史诗宝箱",
  "Units.metalchest.name": "金属",
  "Units.metalchest.stage1.name": "普通宝箱",
  "Units.metalchest.stage2.name": "稀有宝箱",
  "Units.metalchest.stage3.name": "史诗宝箱",
  "Units.icechest.name": "寒冰",
  "Units.icechest.stage1.name": "普通宝箱",
  "Units.icechest.stage2.name": "稀有宝箱",
  "Units.icechest.stage3.name": "史诗宝箱",
  "Units.clothchest.name": "布料",
  "Units.clothchest.stage1.name": "普通宝箱",
  "Units.clothchest.stage2.name": "稀有宝箱",
  "Units.clothchest.stage3.name": "史诗宝箱",
  "Units.japanchest.name": "料理店",
  "Units.japanchest.stage1.name": "普通宝箱",
  "Units.japanchest.stage2.name": "稀有宝箱",
  "Units.japanchest.stage3.name": "史诗宝箱",
  "Units.woodgenerator.stage1.name": "静谧树林",
  "Units.woodgenerator.stage2.name": "微淼之森",
  "Units.woodgenerator.stage3.name": "远古之森",
  "Units.lavagenerator.stage1.name": "燃烧要塞",
  "Units.lavagenerator.stage2.name": "孱弱魔像",
  "Units.lavagenerator.stage3.name": "火焰魔像",
  "Units.jadegenerator.stage1.name": "巨龙废墟",
  "Units.jadegenerator.stage2.name": "龙宝宝",
  "Units.jadegenerator.stage3.name": "翡翠巨龙",
  "Units.metalgenerator.stage1.name": "金属傀儡",
  "Units.metalgenerator.stage2.name": "钢铁机器人",
  "Units.metalgenerator.stage3.name": "机械主厨",
  "Units.icegenerator.stage1.name": "冰封洞穴",
  "Units.icegenerator.stage2.name": "寒冰魔像",
  "Units.icegenerator.stage3.name": "巨型寒冰魔像",
  "Units.clothgenerator.stage1.name": "巨型织布机",
  "Units.clothgenerator.stage2.name": "狮晶角兽",
  "Units.clothgenerator.stage3.name": "蓝羽角兽",
  "Units.japangenerator.stage1.name": "角目丸",
  "Units.japangenerator.stage2.name": "鬼耳武士",
  "Units.japangenerator.stage3.name": "战鬼武士",
  "Units.wands.name": "厨师帽",
  "Units.wands.stage1.name": "1级（5）",
  "Units.wands.stage2.name": "2级（15）",
  "Units.wands.stage3.name": "3级（45）",
  "Units.wands.stage4.name": "4级（135）",
  "Units.wands.stage5.name": "5级（405）",
  "Units.wands.stage6.name": "6级（1215）",
  "Units.coins.name": "金币",
  "Units.coins.stage1.name": "1级",
  "Units.coins.stage2.name": "2级（1）",
  "Units.coins.stage3.name": "3级（3）",
  "Units.coins.stage4.name": "4级（10）",
  "Units.coins.stage5.name": "5级（30）",
  "Units.coins.stage6.name": "6级（90）",
  "Units.coins.stage7.name": "7级（270）",
  "Units.coins.stage8.name": "8级（810）",
  "Units.rubies.name": "钻石",
  "Units.rubies.stage1.name": "1级",
  "Units.rubies.stage2.name": "2级（2）",
  "Units.rubies.stage3.name": "3级（6）",
  "Units.rubies.stage4.name": "4级（20）",
  "Units.rubies.stage5.name": "5级（60）",
  "Units.rubies.stage6.name": "6级（180）",
  "Units.worker.name": "机械工人",
  "Units.worker.stage1.name": "螺栓",
  "Units.worker.stage2.name": "金属臂",
  "Units.worker.stage3.name": "机械骨骼",
  "Units.worker.stage4.name": "动力外骨骼",
  "Units.worker.stage5.name": "机械工人",
  "Units.crystal.name": "神圣符石",
  "Units.crystal.stage1.name": "惊奇符石",
  "Units.crystal.stage2.name": "溢彩符石",
  "Units.crystal.stage3.name": "奥秘符石",
  "Units.crystal.stage4.name": "神圣符石",
  "Units.magicplant.name": "众神林苑",
  "Units.magicplant.stage1.name": "魔法种子",
  "Units.magicplant.stage2.name": "闪耀之根",
  "Units.magicplant.stage3.name": "光辉幼苗",
  "Units.magicplant.stage4.name": "秘术之苗",
  "Units.magicplant.stage5.name": "梦幻之藤",
  "Units.magicplant.stage6.name": "穹顶灌木",
  "Units.magicplant.stage7.name": "神谕林地",
  "Units.magicplant.stage8.name": "超凡灌木丛",
  "Units.magicplant.stage9.name": "众神林苑",
  "Units.energyplant.name": "能量塔",
  "Units.energyplant.stage1.name": "1级能量塔",
  "Units.energyplant.stage2.name": "2级能量塔",
  "Units.energyplant.stage3.name": "3级能量塔",
  "Units.coinsplant.name": "金钱树",
  "Units.coinsplant.stage1.name": "1级金钱树",
  "Units.coinsplant.stage2.name": "2级金钱树",
  "Units.coinsplant.stage3.name": "3级金钱树",
  "Units.rubiesplant.name": "秘术钻石植物丛",
  "Units.rubiesplant.stage1.name": "1级钻石灌木丛",
  "Units.rubiesplant.stage2.name": "2级钻石灌木丛",
  "Units.rubiesplant.stage3.name": "3级钻石灌木丛",
  "Units.woodsource.name": "木材资源",
  "Units.woodsource.stage1.name": "孱弱的树根",
  "Units.woodsource.stage2.name": "孱弱的树苗",
  "Units.woodsource.stage3.name": "邪恶的树根",
  "Units.woodsource.stage4.name": "邪恶的树苗",
  "Units.woodsource.stage5.name": "强壮的树根",
  "Units.woodsource.stage6.name": "强壮的树干",
  "Units.lavasource.name": "熔岩资源",
  "Units.lavasource.stage1.name": "幼年魔像",
  "Units.lavasource.stage2.name": "幼年斯通斯特",
  "Units.lavasource.stage3.name": "少年魔像",
  "Units.lavasource.stage4.name": "少年斯通斯特",
  "Units.lavasource.stage5.name": "成年魔像",
  "Units.lavasource.stage6.name": "成年斯通斯特",
  "Units.jadesource.name": "翡翠原石资源",
  "Units.jadesource.stage1.name": "绿蛋",
  "Units.jadesource.stage2.name": "绿龙雕像",
  "Units.jadesource.stage3.name": "红蛋",
  "Units.jadesource.stage4.name": "红龙雕像",
  "Units.jadesource.stage5.name": "斑点蛋",
  "Units.jadesource.stage6.name": "斑点龙雕像",
  "Units.metalsource.name": "金属资源",
  "Units.metalsource.stage1.name": "初级炼铁厂",
  "Units.metalsource.stage2.name": "初级铁锅",
  "Units.metalsource.stage3.name": "中级炼铁厂",
  "Units.metalsource.stage4.name": "中级铁锅",
  "Units.metalsource.stage5.name": "高级炼铁厂",
  "Units.metalsource.stage6.name": "高级铁锅",
  "Units.icesource.name": "寒冰资源",
  "Units.icesource.stage1.name": "幼年冰魔",
  "Units.icesource.stage2.name": "幼年捕食者",
  "Units.icesource.stage3.name": "少年冰魔",
  "Units.icesource.stage4.name": "少年捕食者",
  "Units.icesource.stage5.name": "成年冰魔",
  "Units.icesource.stage6.name": "成年捕食者",
  "Units.clothsource.name": "布料资源",
  "Units.clothsource.stage1.name": "线轴",
  "Units.clothsource.stage2.name": "线轴妖",
  "Units.clothsource.stage3.name": "针线",
  "Units.clothsource.stage4.name": "缝合妖",
  "Units.clothsource.stage5.name": "盘线",
  "Units.clothsource.stage6.name": "盘线妖",
  "Units.japansource.name": "料理店资源",
  "Units.japansource.stage1.name": "树叶",
  "Units.japansource.stage2.name": "树叶妖",
  "Units.japansource.stage3.name": "树桩花",
  "Units.japansource.stage4.name": "树桩花精",
  "Units.japansource.stage5.name": "紫花树",
  "Units.japansource.stage6.name": "紫花树怪",
  "Units.dishes.name": "食谱",
  "Units.dishes.icecream.name": "烤土豆",
  "Units.dishes.cookies.name": "苹果派",
  "Units.dishes.gingerbread.name": "辣椒芝士薯条",
  "Units.dishes.croissant.name": "豪华玉米片",
  "Units.dishes.caramelpie.name": "葡萄干曲奇",
  "Units.dishes.bakedapple.name": "味增汤",
  "Units.dishes.applejam.name": "炒臭豆腐",
  "Units.dishes.caramelapple.name": "杏仁布丁",
  "Units.dishes.applepie.name": "蘑菇天妇罗",
  "Units.dishes.strawberryjuice.name": "大豆汉堡",
  "Units.dishes.strawberrycake.name": "杏仁蛋糕",
  "Units.dishes.salad.name": "冰激凌",
  "Units.dishes.bubblegum.name": "葡萄果酱",
  "Units.dishes.granola.name": "丝滑圣代",
  "Units.dishes.strawberrypie.name": "芝士包",
  "Units.dishes.mushroomcnacks.name": "石炉披萨",
  "Units.dishes.mintcookies.name": "爆炸蛋糕",
  "Units.dishes.stage18.name": "橘子玛德琳蛋糕",
  "Units.dishes.stage19.name": "蘑菇焗芝士",
  "Units.dishes.stage20.name": "大号水饺",
  "Units.bunny.name": "梦想者梅",
  "Units.bunny.stage1.name": "魔法天梯",
  "Units.bunny.stage2.name": "梦想者梅",
  "Units.tiger.name": "暴躁的虎哥",
  "Units.tiger.stage1.name": "粗糙的厨刀",
  "Units.tiger.stage2.name": "附魔厨刀",
  "Units.tiger.stage3.name": "皇家厨刀",
  "Units.tiger.stage4.name": "暴躁的虎哥",
  "Units.cat.name": "无畏的猫姐",
  "Units.cat.stage1.name": "百吉饼切片器",
  "Units.cat.stage2.name": "松饼铲",
  "Units.cat.stage3.name": "巧克力蛋糕终结者",
  "Units.cat.stage4.name": "切派刀",
  "Units.cat.stage5.name": "糕点铲",
  "Units.cat.stage6.name": "皇家蛋糕切刀",
  "Units.cat.stage7.name": "无畏的猫姐",
  "Units.panda.name": "悠哉的熊猫大侠",
  "Units.panda.stage1.name": "煎蛋锅",
  "Units.panda.stage2.name": "薄饼煎锅",
  "Units.panda.stage3.name": "炒锅",
  "Units.panda.stage4.name": "黄金锅贴煎锅",
  "Units.panda.stage5.name": "意面平底锅",
  "Units.panda.stage6.name": "炖菜砂锅",
  "Units.panda.stage7.name": "多用途怪锅",
  "Units.panda.stage8.name": "悠哉的熊猫大侠",
  "Units.raccoon.name": "快手弗罗浣",
  "Units.raccoon.stage1.name": "微型擀面杖",
  "Units.raccoon.stage2.name": "小号擀面杖",
  "Units.raccoon.stage3.name": "常规擀面杖",
  "Units.raccoon.stage4.name": "面团擀面杖",
  "Units.raccoon.stage5.name": "面包屑制造者",
  "Units.raccoon.stage6.name": "薄饼碾碎器",
  "Units.raccoon.stage7.name": "拉面神杖",
  "Units.raccoon.stage8.name": "皇家擀面杖",
  "Units.raccoon.stage9.name": "快手弗罗浣",
  "Units.fox.name": "狡黠的沃尔狐",
  "Units.fox.stage1.name": "快搅棒",
  "Units.fox.stage2.name": "搅飞棒",
  "Units.fox.stage3.name": "混合棒",
  "Units.fox.stage4.name": "搅拌棒",
  "Units.fox.stage5.name": "搅拌神器",
  "Units.fox.stage6.name": "丝滑制造者",
  "Units.fox.stage7.name": "史诗搅拌棒",
  "Units.fox.stage8.name": "传说搅拌棒",
  "Units.fox.stage9.name": "“搅天拌地”",
  "Units.fox.stage10.name": "狡黠的沃尔狐",
  "Units.dog.name": "温柔的丽莎",
  "Units.dog.stage1.name": "小木桨",
  "Units.dog.stage2.name": "精致木桨",
  "Units.dog.stage3.name": "高级木浆",
  "Units.dog.stage4.name": "铁桨",
  "Units.dog.stage5.name": "精致铁桨",
  "Units.dog.stage6.name": "高级铁桨",
  "Units.dog.stage7.name": "烹饪桨",
  "Units.dog.stage8.name": "精致烹饪桨",
  "Units.dog.stage9.name": "高级烹饪桨",
  "Units.dog.stage10.name": "传说烹饪桨",
  "Units.dog.stage11.name": "温柔的丽莎",
  "Units.hero1.name": "未知英雄",
  "Units.hero2.name": "未知英雄",
  "Units.hero3.name": "未知英雄",
  "Units.hero4.name": "未知英雄",
  "Units.hero5.name": "未知英雄",
  "Units.unknownHero.title": "未知英雄",
  "Units.unknownHero.details": "继续游戏就可以解锁该角色。",
  "Menubar.Orders": "订单",
  "Menubar.Quests": "任务",
  "QuestsWindow.title": "任务",
  "Menubar.Regions": "地区",
  "StartQuestWindow.title": "新任务",
  "FinishQuestWindow.title": "任务完成",
  "FinishQuestWindow.reward": "您的奖励：",
  "Fog.clear": "探索土地",
  "Tutorial.bunny.step1": "刚刚发生了什么？！我是在做梦吗？这个地方看起来可真是太美妙了！咦？这里有几个闪亮的勺子，我试着把它们合成一下看看吧。",
  "Tutorial.wheat_3_tutorial.step1_1": "这里到处充满了生机，真等不及想去看看它的全貌！你看眼前这几个叶苗，合成之后说不定也会发生奇妙的事情。",
  "Tutorial.wheat_3_tutorial.step1_2": "真是小菜一碟，这活我能轻松干一整天，看我给你再搞定一个！",
  "Tutorial.wheat_3_tutorial.step2_1": "快看，这好像是土豆的幼苗，或许合成它们，我们就有新鲜的土豆吃了！",
  "Tutorial.wheat_3_tutorial.step2_2": "我们得先把这些土豆再移近一点，这样我们就能继续合成它们了！",
  "Tutorial.wheat_3_tutorial.step3": "还差一步了！我们把这几个合成后，肯定会是一个大丰收！",
  "Tutorial.dishes_0.step1": "快看，这土豆长的多好，我们快收获吧，正好我有一个烤土豆的配方，让我来给你露一手！",
  "Tutorial.dishes_0.step2": "哇，这次的土豆还真是不少，把它们都捡起来吧，我可以多做几份烤土豆出来。",
  "Tutorial.dishes_0.step3": "太棒了，现在我们有了第一份烤土豆！",
  "Tutorial.dishes_0.step4": "烤土豆只是小试牛刀，对于我这个未来的超级烹饪大师而言，没什么是能难住我的！",
  "Tutorial.dishes_0.step5": "是厨师帽！这可是好东西，有了它，我就可以解锁更多的区域，探索更多的食材了！",
  "Tutorial.dishes_0.step6": "出发吧！让我们看看什么样的冒险在等着我们！",
  "Tutorial.woodsource_1.step1": "听说你想成为顶级的主厨是吗？我们得先有一个足够大的厨房才行，木头继续砍起来！时间可不等人！",
  "Tutorial.woodsource_1.step2": "真棒！我们得把这些木头收集起来，有了它们，离建造一个世界顶级的餐厅就不远了。",
  "Tutorial.woodsource_1.step2_2": "让我们把这些看下来的木头合并成木板材吧。",
  "Tutorial.woodsource_1.step3": "这里将来一定会是特别壮观的景象，当然，我们现在得先开始把这里清理一下。",
  "Tutorial.woodsource_1.step4": "嘘，我知道有办法能加快砍木头的过程，你想试试吗？",
  "Tutorial.woodsource_1.step5": "这么大一个宝箱，看来遇到我之后，你的运气真的变好了！",
  "Tutorial.woodsource_1.step6": "还等什么，咱们快看看宝箱里都有什么！",
  "Tutorial.woodsource_1.step7": "作为一个专业人士，我要告诉你的是，你只需要同时合并5个木头，就能得到2个木材板，每次都能省出1个木头，这就是所谓的生产力提高！",
  "Tutorial.woodsource_1.step8": "又是厨师帽，我获得越多的厨师帽，就能解锁更多的土地！",
  "Workers.busy": "别再胡闹了，我可正忙着呢。",
  "Spawn.nospace": "可用空间不足!",
  "FogBlockedGround.clickMessage": "清除障碍物",
  "CenterHint.merge.begins": "合成",
  "CenterHint.merge.ends": "并且获得",
  "CenterHint.merge.beginsExtra": "合成更多",
  "CenterHint.merge.endsExtra": "并获得额外收益",
  "Dialogue.person.worker": "猴子",
  "Dialogue.person.bunny": "梅",
  "Dialogue.person.tiger": "虎哥",
  "Dialogue.person.cat": "猫姐",
  "Dialogue.person.panda": "熊猫大侠",
  "Dialogue.person.fox": "沃尔狐",
  "Dialogue.person.raccoon": "弗罗浣",
  "Dialogue.person.dog": "丽莎",
  "Quest.spawn.title": "生产项目",
  "Quest.mine.title": "矿石资源",
  "Quest.build.title": "架设大楼",
  "Quest.openfog.title": "征服新区域",
  "Quest.harvest.title": "收集物品",
  "QuestsWindow.find": "寻找",
  "Quest.find.empty": "找不到任何东西",
  "Shop.Gold500.Title": "小堆钻石",
  "Shop.Gold500.Description": "小堆钻石-包含%{diamonds}颗钻石！",
  "Shop.Gold1800.Title": "中堆钻石",
  "Shop.Gold1800.Description": "中堆钻石-包含%{diamonds}颗钻石！",
  "Shop.Gold3800.Title": "大堆钻石",
  "Shop.Gold3800.Description": "大堆钻石-包含%{diamonds}颗钻石！",
  "Shop.Gold6000.Title": "钻石山",
  "Shop.Gold6000.Description": "钻石山-包含%{diamonds}颗钻石！",
  "Shop.Gold25000.Title": "钻石宝藏",
  "Shop.Gold25000.Description": "钻石宝藏-包含%{diamonds}颗钻石！",
  "Product.YouBought": "您购买了%{coins}颗钻石!",
  "CastleGuideWindow.firstStage": "合成资源",
  "CastleGuideWindow.secondStage": "升级建筑",
  "CastleGuideWindow.thirdStage": "从最终建筑中获得奖励",
  "GeneratorGuideWindow.firstStage": "升级你的生物",
  "GeneratorGuideWindow.secondStage": "取得产品",
  "GeneratorGuideWindow.thirdStage": "合成它们来获得资源",
  "CrystalGuideWindow.firstStage": "合成魔术石",
  "CrystalGuideWindow.secondStage": "获得神圣符石",
  "CrystalGuideWindow.thirdStage": "生产任何新物品时都可以将其用作缺少的物品",
  "InstantWorkerGuideWindow.firstStage": "合并备件",
  "InstantWorkerGuideWindow.secondStage": "创建机械工人",
  "InstantWorkerGuideWindow.thirdStage": "使用它们来加快施工速度",
  "EnergyLotteryWindow.title": "抽奖",
  "EnergyLotteryWindow.description": "获得每日免费能量!",
  "EnergyForVideoProduct.description": "观看广告获得额外能量!",
  "EnergyForVideoProduct.waiting": "可用于",
  "EnergyForVideoProduct.notAvailable": "广告不可用",
  "BuyEnergyProduct.description": "获得额外的能量!",
  "BuyEnergyProduct.waiting": "可用于",
  "EnergyLotteryProduct.description": "获得每日免费能量!",
  "EnergyLotteryProduct.waiting": "可用于",
  "Fog.clear.levelCondition": "您必须达到%{level}级才能探索这片土地",
  "Fog.clear.heroCondition": "您需要%{hero}来探索这片土地",
  "FbConnectWindow.text": "要保存进度，请连接您的%{facebook}帐户!",
  "Units.herochest.stage1.name": "主厨宝箱",
  "Units.freechest.stage1.name": "免费宝箱",
  "Units.sharechest.stage1.name": "好友宝箱",
  "UnitsShop.IconForce": "在市场上领取你的每天免费物品！",
  "UnitsShop.title": "市场",
  "UnitsShop.left": "剩余：%{left}",
  "UnitsShop.newItemsWillAppear": "新物品将出现在",
  "UnitsShop.reset": "重启",
  "EnergyLotteryProduct.level": "%{level}级",
  "SpecialOfferWindow.title": "特价!",
  "SpecialOfferWindow.text": "您想再买一件吗？",
  "SpecialOfferView.buy": "买",
  "SpecialOfferWindow.timer": "就是现在",
  "SpecialOfferWindow.timeIsOver": "时间到",
  "SpecialOfferWindow.pass": "不，谢谢",
  "moneyFog.adsTip1": "看广告减%{diamonds}",
  "moneyFog.adsTip2": "*每次观看广告都会减少所需钻石数量",
  "moneyFog.buyNow": "立即购买",
  "moneyFog1.name": "黄油蛋糕岛",
  "moneyFog1.text": "哇，有什么能比一个黄油蛋糕岛更好呢，除了 %{tiles} 额外的地块还有大把的宝藏，这些可都能帮助你的兔梅实现她伟大的主厨梦想哦！",
  "moneyFog2.name": "草莓芭菲岛",
  "moneyFog2.text": "这个岛不光看着美味，还有大量的地块和宝藏哦！\n",
  "moneyFog2.tip1": "%{amount} 额外的地块",
  "moneyFog.tip": "大量宝藏",
  "moneyFog3.name": "山核桃派岛",
  "moneyFog3.text": "获得%{tiles}额外的蛋糕，哦不对，是地块！当然也少不了神奇的宝藏，只有最尊贵的人才值得拥有它们，不是吗？",
  "moneyFog4.name": "魔法华夫饼岛",
  "moneyFog4.text": "看起来这个就是终极至尊岛了！既有%{tiles}额外的地块，还有无数人梦寐以求的宝物，更不用说它看起来就像华夫冰激凌，为什么我对着一个岛在流口水？",
  "cantCollectBuilding": "您需要建立%{target}来收集!",
  "Quest.hero.title": "召唤英雄",
  "ChestContainAmount": "包含%{min}至%{max}个物品：",
  "ChestContainSameItems": "*可能包含多个相同的物品",
  "OrdersWindow.orders.title": "订单",
  "OrdersWindow.recipes.title": "菜品",
  "OrdersWindow.ingredients.title": "食材",
  "BattlePassWindow.title": "芝士收获季",
  "BattlePassWindow.timer": "剩余时间：",
  "BattlePassWindow.progress": "下一个奖励",
  "BattlePassWindow.ticket.hint": "您需要超级芝士票才能获得超级奖励!",
  "BattlePassWindow.ticket.hint.active": "超级芝士票有效!",
  "BattlePassWindow.description": "架设建筑物以获得芝士并赢得奖励!",
  "BattlePassWindow.moreStarsToolTip": "您需要更多的星星!",
  "BattlePassWindow.needPremiumToolTip": "您需要获得超级芝士来领取奖励！",
  "BattlePassWindow.finished": "赛季结束",
  "BattlePassRulesWindow.title": "建造季",
  "BattlePassRulesWindow.description": "购买芝士票即可参加此活动!随着您的进步，将会获得更多奖励!",
  "BattlePassRulesWindow.firstStage": "架设建筑物",
  "BattlePassRulesWindow.secondStage": "收集芝士",
  "BattlePassRulesWindow.thirdStage": "获得奖励",
  "BattlePassProduct.Title": "超级芝士",
  "BarrelAdsWindow.title": "选择奖励",
  "BarrelAdsWindow.subTitle": "观看视频并选择奖励",
  "Unit.Developing": "这个单元目前正在开发中，即将推出。",
  "Fog.clear.notEnoughWands": "您缺少%{wands}个厨师帽来探索这些土地",
  "Fog.clear.clearNow": "您可以立即探索这些土地!",
  "InfoView.button.remove": "去除",
  "InfoView.button.exchange": "兑换",
  "RemoveUnitWindow.title": "去除",
  "RemoveUnitWindow.text": "您确定要永久删除该对象吗？",
  "InfoView.button.level": "%{level}级",
  "Units.dragonmine.stage1.name": "龙矿",
  "BattlePassLastChanceWindow.title": "很近",
  "BattlePassLastChanceWindow.upperText": "这个奖励眼看就是你的了！",
  "BattlePassLastChanceWindow.lowerText": "这是您获得这个奖励的最后机会!",
  "BattlePassLastChanceWindow.badgeText": "最后的机会",
  "BattlePassRewardIcon.ribbonText": "超级芝士",
  "BuyEnergy.IconForce": "更多能量代表着更久的游戏时长，冲啊！",
  "UnitsLibrary.IconForce": "一本菜单？让我们看看里面有什么！",
  "Paint.force": "绘制",
  "LivesShopWindow.products.energyForVideoShort": "5",
  "StickersCollectionWindow.Title": "当前无法实现",
  "SubscriptionWindow.Title": "订阅",
  "SubscriptionWindow.note": "当前无法实现",
  "SubscriptionWindow.RewardTimerDescription": "当前无法实现",
  "ConfirmExitWindow.text": "当前无法实现",
  "SpecialEnergyOfferWindow.title": "能量",
  "SpecialEnergyOfferWindow.text": "现在购买,再送 %{amount}\n合计：",
  "Quest.woodgenerator_1.title": "找到木头来源",
  "Quest.r_collectfruit.title": "收集植物",
  "Quest.r_createfruit.title": "创建水果",
  "Quest.r_bonusmerge.title": "额外合成",
  "Quest.r_open_chest.title": "打开宝箱",
  "Quest.r_open_randomchest.title": "打开宝箱",
  "Quest.r_use_randomcastle.title": "建造城堡",
  "Quest.r_use_randommine.title": "建造矿井",
  "Quest.r_builditems.title": "找到物品",
  "Menubar.Menu": "菜单",
  "Menubar.Special": "特卖",
  "Menubar.Subscription": "订阅",
  "Menubar.Market": "市场",
  "Menubar.Daily": "任务",
  "Menubar.Login": "登录奖励",
  "DailyMissionsWindow.title": "每日任务",
  "MailWindow.title": "邮件",
  "MailWindow.rewards": "奖励",
  "MailWindow.noMails": "没有邮件",
  "MailWindow.selectMail": "请选择一封邮件",
  "MailWindow.expiringSoon": "所剩时间不多了",
  "MailWindow.cantGetMail": "不能读取这封邮件，请稍后重试。",
  "DeliciousWindow.title": "美食广场",
  "DeliciousWindow.info": "美食广场是美食的天堂，充满活力的美食摊位和餐厅提供各种全球美食，将给吃货们创造难忘的体验。",
  "DeliciousWindow.leftTime": "剩余时间：",
  "Units.delicious_pizza.name": "披萨",
  "Units.delicious_pizza.stage1.name": "意式美味",
  "Units.delicious_pizza.stage2.name": "脆皮风情",
  "Units.delicious_pizza.stage3.name": "招牌美味",
  "Units.delicious_pizza.stage4.name": "欢乐比萨",
  "Units.delicious_pizza.stage5.name": "浓情薄饼",
  "Units.delicious_pizza.stage6.name": "披萨天堂",
  "Units.delicious_pizza.stage7.name": "番茄芝士",
  "Units.delicious_pizza.stage8.name": "火焰风暴",
  "Units.delicious_pizza.stage9.name": "蔬果缤纷",
  "Units.delicious_pizza.stage10.name": "招牌独享",
  "Units.delicious_pizza.stage11.name": "海鲜盛宴",
  "Units.delicious_hamburger.name": "汉堡",
  "Units.delicious_hamburger.stage1.name": "早餐之王汉堡",
  "Units.delicious_hamburger.stage2.name": "辣味特攻汉堡",
  "Units.delicious_hamburger.stage3.name": "经典美式汉堡",
  "Units.delicious_hamburger.stage4.name": "金牌芝士汉堡",
  "Units.delicious_hamburger.stage5.name": "牛肉狂潮汉堡",
  "Units.delicious_hamburger.stage6.name": "意式风情汉堡",
  "Units.delicious_hamburger.stage7.name": "蘑菇幻想汉堡",
  "Units.delicious_hamburger.stage8.name": "火鸡狂欢汉堡",
  "Units.delicious_hamburger.stage9.name": "太空探险汉堡",
  "Units.delicious_hamburger.stage10.name": "绿野仙踪汉堡",
  "Units.delicious_hamburger.stage11.name": "熊猫汉堡",
  "Units.delicious_steak.name": "牛排",
  "Units.delicious_steak.stage1.name": "经典肉眼牛排",
  "Units.delicious_steak.stage2.name": "焦糖烧烤西冷牛排",
  "Units.delicious_steak.stage3.name": "黑胡椒爱尔兰牛排",
  "Units.delicious_steak.stage4.name": "威士忌熏烤牛排",
  "Units.delicious_steak.stage5.name": "美国田园牛排",
  "Units.delicious_steak.stage6.name": "秘制香草黄油牛排",
  "Units.delicious_steak.stage7.name": "肉汁流溢阿根廷牛排",
  "Units.delicious_steak.stage8.name": "加勒比海鱼汁牛排",
  "Units.delicious_steak.stage9.name": "墨西哥辣椒牛排",
  "Units.delicious_steak.stage10.name": "奶酪之恋牛排",
  "Units.delicious_steak.stage11.name": "芝士控的梦想牛排",
  "Units.delicious_sushi.name": "寿司",
  "Units.delicious_sushi.stage1.name": "黄金之梦",
  "Units.delicious_sushi.stage2.name": "珍宝卷",
  "Units.delicious_sushi.stage3.name": "红鲤樱花卷",
  "Units.delicious_sushi.stage4.name": "海之花",
  "Units.delicious_sushi.stage5.name": "赤焰龙虾卷",
  "Units.delicious_sushi.stage6.name": "美味绘卷",
  "Units.delicious_sushi.stage7.name": "珊瑚盛宴",
  "Units.delicious_sushi.stage8.name": "金鲨翻滚",
  "Units.delicious_sushi.stage9.name": "樱花之舞",
  "Units.delicious_sushi.stage10.name": "五彩缤纷盘",
  "Units.delicious_sushi.stage11.name": "海之盛宴",
  "Units.delicious_pasta.name": "意大利面",
  "Units.delicious_pasta.stage1.name": "罗马之夜意面",
  "Units.delicious_pasta.stage2.name": "阳光通心粉",
  "Units.delicious_pasta.stage3.name": "香蒜奶油意面",
  "Units.delicious_pasta.stage4.name": "阳光番茄意面",
  "Units.delicious_pasta.stage5.name": "野菇白酱面",
  "Units.delicious_pasta.stage6.name": "意大利肉丸面",
  "Units.delicious_pasta.stage7.name": "奶酪炙烤通心粉",
  "Units.delicious_pasta.stage8.name": "香烤意大利香肠面",
  "Units.delicious_pasta.stage9.name": "田园蔬菜通心粉",
  "Units.delicious_pasta.stage10.name": "地中海海鲜意面",
  "Units.delicious_pasta.stage11.name": "意大利经典千层面",
  "Units.delicious_icecream.name": "冰淇淋",
  "Units.delicious_icecream.stage1.name": "美味甜筒",
  "Units.delicious_icecream.stage2.name": "梦幻覆盆子雪山",
  "Units.delicious_icecream.stage3.name": "夏日草莓梦幻筒",
  "Units.delicious_icecream.stage4.name": "阳光柠檬雪芭",
  "Units.delicious_icecream.stage5.name": "爱琴海蓝柚子海岸",
  "Units.delicious_icecream.stage6.name": "橙花覆盆子冰瀑",
  "Units.delicious_icecream.stage7.name": "蜜糖杏仁巧克力梦",
  "Units.delicious_icecream.stage8.name": "玫瑰覆盆子夏之梦",
  "Units.delicious_icecream.stage9.name": "精灵蓝莓薄荷",
  "Units.delicious_icecream.stage10.name": "巧克力榛果仙境",
  "Units.delicious_icecream.stage11.name": "天使之吻芒果波波",
  "Units.deliciouschest.name": "美食广场",
  "Units.deliciouschest.stage1.name": "普通宝箱",
  "Units.deliciouschest.stage2.name": "稀有宝箱",
  "Units.deliciouschest.stage3.name": "史诗宝箱",
  "Units.deliciousfreechest.stage1.name": "美食宝箱",
  "Units.deliciousluxurychest.stage1.name": "豪华美食宝箱",
  "Units.deliciouschest_hamburger.name": "汉堡",
  "Units.deliciouschest_hamburger.stage1.name": "普通宝箱",
  "Units.deliciouschest_hamburger.stage2.name": "稀有宝箱",
  "Units.deliciouschest_hamburger.stage3.name": "史诗宝箱",
  "Units.deliciousfreechest_hamburger.stage1.name": "美食宝箱",
  "Units.deliciousluxurychest_hamburger.stage1.name": "豪华美食宝箱",
  "Units.deliciouschest_steak.name": "牛排",
  "Units.deliciouschest_steak.stage1.name": "普通宝箱",
  "Units.deliciouschest_steak.stage2.name": "稀有宝箱",
  "Units.deliciouschest_steak.stage3.name": "史诗宝箱",
  "Units.deliciousfreechest_steak.stage1.name": "美食宝箱",
  "Units.deliciousluxurychest_steak.stage1.name": "豪华美食宝箱",
  "Units.deliciouschest_sushi.name": "寿司",
  "Units.deliciouschest_sushi.stage1.name": "普通宝箱",
  "Units.deliciouschest_sushi.stage2.name": "稀有宝箱",
  "Units.deliciouschest_sushi.stage3.name": "史诗宝箱",
  "Units.deliciousfreechest_sushi.stage1.name": "美食宝箱",
  "Units.deliciousluxurychest_sushi.stage1.name": "豪华美食宝箱",
  "Units.deliciouschest_pasta.name": "寿司",
  "Units.deliciouschest_pasta.stage1.name": "普通宝箱",
  "Units.deliciouschest_pasta.stage2.name": "稀有宝箱",
  "Units.deliciouschest_pasta.stage3.name": "史诗宝箱",
  "Units.deliciousfreechest_pasta.stage1.name": "美食宝箱",
  "Units.deliciousluxurychest_pasta.stage1.name": "豪华美食宝箱",
  "Units.deliciouschest_icecream.name": "冰淇淋",
  "Units.deliciouschest_icecream.stage1.name": "普通宝箱",
  "Units.deliciouschest_icecream.stage2.name": "稀有宝箱",
  "Units.deliciouschest_icecream.stage3.name": "史诗宝箱",
  "Units.deliciousfreechest_icecream.stage1.name": "美食宝箱",
  "Units.deliciousluxurychest_icecream.stage1.name": "豪华美食宝箱",
  "LimitedTimeGiftPack.Title": "新手限时礼包",
  "BuyMonkeyWithDiamond.Title": "更多的工人",
  "BuyMonkeyWithDiamond.onlyNeed": "只需要",
  "BuyMonkeyWithDiamond.onlyNeed_end": "",
  "BattlePassWindow.title_cooking": "厨艺大赛",
  "BattlePassWindow.ticket.hint_cooking": "你需要一本秘籍，就可以获得更多奖励！",
  "BattlePassWindow.ticket.hint.active_cooking": "秘籍生效中…",
  "BattlePassWindow.description_cooking": "完成更多的订单，获得更多的积分。",
  "BattlePassProduct.Title_cooking": "秘籍",
  "CookingRulesWindow.title": "厨艺大赛",
  "CookingRulesWindow.firstStage": "收集植物果实",
  "CookingRulesWindow.secondStage": "烹饪",
  "CookingRulesWindow.thirdStage": "获得奖牌",
  "AdsUnavailable_viber": "广告目前不可用，请看看这个吧。",
  "ViberShareWindow.tip": "你邀请的朋友越多，你得到的奖励就越多，但每天只有一次机会。",
  "ViberShareWindow.tip1": "邀请5位好友即可获得宝箱",
  "ViberShareWindow.tip2": "*不会消耗你的材料哦",
  "ViberShareWindow.gift.sending": "发送",
  "ViberShareWindow.gift.onlyaccept": "只接受",
  "ViberShareWindow.gift.string1": "你收到了",
  "ViberShareWindow.gift.string2": "来自%{name}的礼物，如果你愿意，",
  "ViberShareWindow.gift.string3": "可以把这份善意传递给",
  "ViberShareWindow.thanks.string1": "%{name}送给你",
  "ViberShareWindow.thanks.string2": "，作为回礼，你可以",
  "ViberShareWindow.thanks.string3": "送一个",
  "ViberShareWindow.thanks.string4": "给他。",
  "ViberRebirth": "复活",
  "ViberShareWindow.tip3": "邀请好友可获得%{amount}点能量",
  "ViberShareWindow.tip4": "邀请好友获得宝箱。",
  "Ranking": "排名",
  "extraworker4hours.Title": "4小时",
  "extraworker1day.Title": "1天",
  "extraworker7days.Title": "10天",
  "extraworker4hours.Description": "额外工人增加4小时",
  "extraworker1day.Description": "额外工人增加1天",
  "extraworker7days.Description": "额外工人增加10天",
  "ShopWindow.DoubleRewards": "钻石双倍收益",
  "ShopWindow.more": "再得%{value}",
  "buyEnergy200.description": "买200 送200",
  "endlessenergy1hour.Title": "1小时",
  "endlessenergy1hour.Description": "1小时内无限能量",
  "endlessenergy2hours.Title": "2小时",
  "endlessenergy2hours.Description": "2小时内无限能量",
  "greatsale": "超值出售中！",
  "LoginWindow.title": "登录奖励",
  "LoginWindow.today": "今天",
  "LoginWindow.days": "第%{day}天",
  "postfix.day": "%{day} 天",
  "postfix.days": "%{day} 天",
  "postfix.hour": "%{hour} 小时",
  "postfix.hours": "%{hour} 小时",
  "RegionsWindow.Fogs": "土地",
  "RegionsWindow.Regions": "地区",
  "RegionsWindow.Decorators": "装饰物",
  "EnergyFeastMissionWindow.title": "能量盛宴",
  "EnergyFeastMissionWindow.finished": "完成",
  "EnergyFeastMissionWindow.tooltip.amount": "消耗的能量",
  "CoinsTimeMissionWindow.details.text": "当前无法实现",
  "FeastMissionWindow.finished": "当前无法实现",
  "CoinsFeastMissionWindow.title": "当前无法实现",
  "CoinsFeastMissionWindow.tooltip.amount": "当前无法实现",
  "MergeSubscriptionPrize.subtitle": "当前无法实现",
  "Units.coinsplantchest.name": "金币箱",
  "Units.coinsplantchest.stage1.name": "小金币箱",
  "Units.coinsplantchest.stage2.name": "中金币箱",
  "Units.coinsplantchest.stage3.name": "大金币箱",
  "Units.energyplantchest.name": "能量箱",
  "Units.energyplantchest.stage1.name": "小能量盒",
  "Units.energyplantchest.stage2.name": "中能量盒",
  "Units.energyplantchest.stage3.name": "大能量盒",
  "Units.rubiesplantchest.name": "钻石箱",
  "Units.rubiesplantchest.stage1.name": "小钻石箱",
  "Units.rubiesplantchest.stage2.name": "中钻石箱",
  "Units.rubiesplantchest.stage3.name": "大钻石箱"
}