{
"skeleton": { "hash": "h1WHnGIvs4xQZ9Su/wBw0lxPMEM", "spine": "3.7.94", "width": 224.23, "height": 225.19, "images": "./images/", "audio": "C:/Work/EverMerge/merge/artefact" },
"bones": [
	{ "name": "root" }
],
"slots": [
	{ "name": "artefact_back2", "bone": "root", "color": "ffffff92", "attachment": "artefact_back2" },
	{ "name": "artefact_shadow", "bone": "root", "attachment": "artefact_shadow" },
	{ "name": "artefact_back3", "bone": "root", "attachment": "artefact_back3" }
],
"skins": {
	"default": {
		"artefact_back2": {
			"artefact_back2": { "x": 0.29, "y": 1.86, "scaleX": 0.958, "scaleY": 0.958, "width": 234, "height": 235 }
		},
		"artefact_back3": {
			"artefact_back3": { "x": -1.67, "y": 2.08, "scaleX": 0.527, "scaleY": 0.527, "width": 213, "height": 207 }
		},
		"artefact_shadow": {
			"artefact_shadow": { "x": -0.19, "y": -30.41, "scaleX": 1.299, "scaleY": 0.733, "width": 60, "height": 63 }
		}
	}
},
"animations": {
	"appearance": {
		"slots": {
			"artefact_back2": {
				"color": [
					{ "time": 0, "color": "ffffff00" },
					{ "time": 0.5, "color": "ffffffff" }
				]
			},
			"artefact_back3": {
				"color": [
					{ "time": 0, "color": "ffffff00" },
					{ "time": 0.5, "color": "ffffffff" }
				]
			},
			"artefact_shadow": {
				"color": [
					{ "time": 0, "color": "ffffff00" },
					{ "time": 0.5, "color": "ffffffff" }
				]
			}
		}
	},
	"disappearance": {
		"slots": {
			"artefact_back2": {
				"color": [
					{ "time": 0, "color": "ffffffff" },
					{ "time": 0.1667, "color": "ffffff00" }
				]
			},
			"artefact_back3": {
				"color": [
					{
						"time": 0,
						"color": "ffffffff",
						"curve": [ 0.124, 0.7, 0.75, 1 ]
					},
					{ "time": 0.1667, "color": "ffffff00" }
				]
			},
			"artefact_shadow": {
				"color": [
					{
						"time": 0,
						"color": "ffffffff",
						"curve": [ 0.124, 0.7, 0.75, 1 ]
					},
					{ "time": 0.1667, "color": "ffffff00" }
				]
			}
		}
	},
	"idle": {}
}
}